kaybee_bulma/__init__.py
kaybee_bulma/events.py
kaybee_bulma/index.html
kaybee_bulma/index.tsx
kaybee_bulma/run_livereload.py
kaybee_bulma/siteconfig.py
kaybee_bulma/theme.conf
kaybee_bulma/filteredlisting/Actions.ts
kaybee_bulma/filteredlisting/Author.tsx
kaybee_bulma/filteredlisting/Container.tsx
kaybee_bulma/filteredlisting/Dumpstate.tsx
kaybee_bulma/filteredlisting/Duration.tsx
kaybee_bulma/filteredlisting/Fetching.tsx
kaybee_bulma/filteredlisting/Notification.tsx
kaybee_bulma/filteredlisting/Pagination.tsx
kaybee_bulma/filteredlisting/Reference.tsx
kaybee_bulma/filteredlisting/References.tsx
kaybee_bulma/filteredlisting/Result.tsx
kaybee_bulma/filteredlisting/Results.tsx
kaybee_bulma/filteredlisting/Searchbox.tsx
kaybee_bulma/filteredlisting/Sidebar.tsx
kaybee_bulma/filteredlisting/SidebarCheckbox.tsx
kaybee_bulma/filteredlisting/SidebarRadio.tsx
kaybee_bulma/filteredlisting/SidebarSelect.tsx
kaybee_bulma/filteredlisting/State.ts
kaybee_bulma/filteredlisting/TechLogo.tsx
kaybee_bulma/filteredlisting/__init__.py
kaybee_bulma/filteredlisting/dbjson.spec.ts
kaybee_bulma/filteredlisting/dbjson.ts
kaybee_bulma/filteredlisting/filteredlisting.html
kaybee_bulma/filteredlisting/utils.ts
kaybee_bulma/scss/_breadcrumb.scss
kaybee_bulma/scss/_content.scss
kaybee_bulma/scss/_filteredlisting.scss
kaybee_bulma/scss/_footer.scss
kaybee_bulma/scss/_hero.scss
kaybee_bulma/scss/_homepage.scss
kaybee_bulma/scss/_main.scss
kaybee_bulma/scss/_navbar.scss
kaybee_bulma/scss/_notification.scss
kaybee_bulma/scss/_querylist.scss
kaybee_bulma/scss/_sectionbox.scss
kaybee_bulma/scss/_sidenav.scss
kaybee_bulma/scss/_toctree.scss
kaybee_bulma/scss/kaybee_bulma.scss
kaybee_bulma/scss/pygments.css
kaybee_bulma/static/kaybee_bulma.css
kaybee_bulma/static/kaybee_bulma.js
kaybee_bulma/static/kaybee_bulma.map
kaybee_bulma/static/kaybee_logo.png
kaybee_bulma/static/kaybee_logo.svg
kaybee_bulma/templates/article.html
kaybee_bulma-0.2.31.dist-info/METADATA
kaybee_bulma-0.2.31.dist-info/RECORD
kaybee_bulma-0.2.31.dist-info/WHEEL
kaybee_bulma-0.2.31.dist-info/entry_points.txt
kaybee_bulma-0.2.31.dist-info/top_level.txt
