Metadata-Version: 2.1
Name: kaybee-bulma
Version: 0.2.31
Summary: Bulma-based theme for Kaybee
Home-page: https://github.com/pauleveritt/kaybee_bulma
Author: Paul Everitt
Author-email: pauleveritt@me.com
License: UNKNOWN
Keywords: sphinx theme blog website
Platform: UNKNOWN
Classifier: Development Status :: 3 - Alpha
Classifier: Intended Audience :: Developers
Classifier: Topic :: Software Development :: Documentation
Classifier: License :: OSI Approved :: Apache Software License
Classifier: Programming Language :: Python :: 3.6
Requires-Dist: sphinx
Requires-Dist: kaybee
